[
	{
		"fichier": "carte_potages",
		"titre": "Potages",
		"titre_chinois": "湯",
		"commentaires": ""
	},
	{
		"fichier": "carte_entrees",
		"titre": "Entrées",
		"titre_chinois": "小吃",
		"commentaires": ""
	},
	{
		"fichier": "carte_volailles",
		"titre": "Volailles",
		"titre_chinois": "家禽",
		"commentaires": "Tous nos plats sont servis avec du riz nature"
	},
	{
		"fichier": "carte_viandes",
		"titre": "Viandes",
		"titre_chinois": "肉",
		"commentaires": "Tous nos plats sont servis avec du riz nature"
	},
	{
		"fichier": "carte_fruitsdemer",
		"titre": "Fruits de Mer",
		"titre_chinois": "海鮮",
		"commentaires": "Tous nos plats sont servis avec du riz nature"
	},
	{
		"fichier": "carte_rizetnouilles",
		"titre": "Riz et Nouilles",
		"titre_chinois": "米飯和麵條",
		"commentaires": ""
	},
	{
		"fichier": "carte_desserts",
		"titre": "Desserts",
		"titre_chinois": "甜點",
		"commentaires": ""
	}
]